reinfocus/__init__.py
reinfocus/histories.py
reinfocus/vision.py
reinfocus/environments/__init__.py
reinfocus/environments/environment.py
reinfocus/environments/episode_ender.py
reinfocus/environments/episode_rewarder.py
reinfocus/environments/episode_visualizer.py
reinfocus/environments/state_initializer.py
reinfocus/environments/state_observer.py
reinfocus/environments/state_transformer.py
reinfocus/environments/types.py
reinfocus/environments/vector_environment.py
reinfocus/environments/experimental/__init__.py
reinfocus/environments/experimental/vector_shim.py
reinfocus/graphics/__init__.py
reinfocus/graphics/camera.py
reinfocus/graphics/cutil.py
reinfocus/graphics/device_data.py
reinfocus/graphics/hit_record.py
reinfocus/graphics/physics.py
reinfocus/graphics/random.py
reinfocus/graphics/ray.py
reinfocus/graphics/rectangle.py
reinfocus/graphics/render.py
reinfocus/graphics/shape.py
reinfocus/graphics/shape_factory.py
reinfocus/graphics/sphere.py
reinfocus/graphics/vector.py
reinfocus/graphics/world.py
reinfocus-0.0.2.dist-info/METADATA
reinfocus-0.0.2.dist-info/WHEEL
reinfocus-0.0.2.dist-info/licenses/LICENSE
reinfocus-0.0.2.dist-info/RECORD
