Metadata-Version: 2.3
Name: reinfocus
Version: 0.0.2
Summary: Environments where agents can focus cameras on rendered objects.
Project-URL: Homepage, https://github.com/jeffwhunter/reinfocus
Project-URL: Issues, https://github.com/jeffwhunter/reinfocus/issues
Author-email: Jeff Hunter <jhunter57@gmail.com>
License-File: LICENSE
Classifier: License :: OSI Approved :: MIT License
Classifier: Operating System :: OS Independent
Classifier: Programming Language :: Python :: 3
Classifier: Programming Language :: Python :: 3 :: Only
Classifier: Programming Language :: Python :: 3.11
Classifier: Programming Language :: Python :: 3.12
Classifier: Topic :: Scientific/Engineering
Classifier: Topic :: Scientific/Engineering :: Artificial Intelligence
Classifier: Topic :: Scientific/Engineering :: Mathematics
Classifier: Topic :: Software Development
Classifier: Topic :: Software Development :: Libraries
Classifier: Topic :: Software Development :: Libraries :: Python Modules
Requires-Python: >=3.11
Requires-Dist: gymnasium~=0.29.0
Requires-Dist: matplotlib~=3.8.2
Requires-Dist: numba~=0.59.0
Requires-Dist: numpy~=1.26.4
Requires-Dist: opencv-python~=4.9.0.80
Provides-Extra: examples
Requires-Dist: ipywidgets~=8.1.2; extra == 'examples'
Requires-Dist: notebook~=7.1.3; extra == 'examples'
Requires-Dist: optuna~=3.6.1; extra == 'examples'
Requires-Dist: pygame~=2.5.2; extra == 'examples'
Requires-Dist: pyyaml~=6.0.1; extra == 'examples'
Requires-Dist: rl-zoo3~=2.3.0; extra == 'examples'
Requires-Dist: tensorboard~=2.16.2; extra == 'examples'
